patcherex2/decompiler_plugins/__init__.py
patcherex2/decompiler_plugins/__main__.py
patcherex2/decompiler_plugins/controller.py
patcherex2/decompiler_plugins/installer.py
patcherex2/decompiler_plugins/patcherex2_plugin.py
patcherex2/decompiler_plugins/ui.py
patcherex2/decompiler_plugins/decompiler_specific/deci_extras.py
patcherex2/decompiler_plugins/decompiler_specific/angr/interface.py
patcherex2/decompiler_plugins/decompiler_specific/angr/plugin.toml
patcherex2/decompiler_plugins/decompiler_specific/ghidra/interface.py
patcherex2_decompiler_plugins-0.0.7.dist-info/METADATA
patcherex2_decompiler_plugins-0.0.7.dist-info/WHEEL
patcherex2_decompiler_plugins-0.0.7.dist-info/entry_points.txt
patcherex2_decompiler_plugins-0.0.7.dist-info/top_level.txt
patcherex2_decompiler_plugins-0.0.7.dist-info/RECORD
