Metadata-Version: 2.2
Name: patcherex2-decompiler-plugins
Version: 0.0.7
Project-URL: Homepage, https://github.com/purseclab/Patcherex2-Extras
Project-URL: Source, https://github.com/purseclab/Patcherex2-Extras
Project-URL: Tracker, https://github.com/purseclab/Patcherex2-Extras/issues
Requires-Python: >=3.8
Requires-Dist: patcherex2
Requires-Dist: libbs
